aestimo/CODE_OF_CONDUCT.md
aestimo/COPYING.md
aestimo/README.md
aestimo/__init__.py
aestimo/aestimo.py
aestimo/config.py
aestimo/database.py
aestimo/database1.py
aestimo/intersubband_optical_transitions.py
aestimo/main.py
aestimo/main_iterating.py
aestimo/aeslibs/VBHM.py
aestimo/aeslibs/__init__.py
aestimo/aeslibs/aestimo_poisson1d.py
aestimo/aeslibs/ddgelectron_driftdiffusion.py
aestimo/aeslibs/ddggummelmap.py
aestimo/aeslibs/ddghole_driftdiffusion.py
aestimo/aeslibs/ddgnlpoisson.py
aestimo/aeslibs/ddnnewtonmap.py
aestimo/aeslibs/func_lib.py
aestimo/examples/sample_1qw_barrierdope_ingaas.py
aestimo/examples/sample_2qw_InGaAS_GaAs.py
aestimo/examples/sample_2qw_InGaN_GaN_vs_1ddcc.py
aestimo/examples/sample_2qw_barrierdope_ingaas.py
aestimo/examples/sample_double_qw.py
aestimo/examples/sample_double_qw_isbt.py
aestimo/examples/sample_moddop.py
aestimo/examples/sample_mqw_barrierdope_p_ingan.py
aestimo/examples/sample_mqw_barrierdope_p_ingan_2.py
aestimo/examples/sample_multi_qw_barrierdope_p.py
aestimo/examples/sample_multi_qw_barrierdope_p2.py
aestimo/examples/sample_multi_qw_barrierdope_p_ingan.py
aestimo/examples/sample_pn.py
aestimo/examples/sample_pn2.py
aestimo/examples/sample_pn3.py
aestimo/examples/sample_qw_HarrisonCh3_3.py
aestimo/examples/sample_qw_HarrisonCh3_5.py
aestimo/examples/sample_qw_barrierdope.py
aestimo/examples/sample_qw_barrierdope_ingaas.py
aestimo/examples/sample_qw_barrierdope_ingan.py
aestimo/examples/sample_qw_barrierdope_ingan_2.py
aestimo/examples/sample_qw_barrierdope_p.py
aestimo/examples/sample_qw_barrierdope_p_AlGaInN.py
aestimo/examples/sample_qw_barrierdope_p_AlGaInN_2.py
aestimo/examples/sample_qw_barrierdope_p_InGaAsP.py
aestimo/examples/sample_qw_barrierdope_p_algan_gan_heterojunction.py
aestimo/examples/sample_qw_barrierdope_p_cdzno.py
aestimo/examples/sample_qw_barrierdope_p_ingaas.py
aestimo/examples/sample_qw_periodic_potential.py
aestimo/examples/sample_qw_qwdope.py
aestimo/examples/sample_qw_wide_isbt.py
aestimo-3.0.0.dist-info/COPYING.md
aestimo-3.0.0.dist-info/METADATA
aestimo-3.0.0.dist-info/WHEEL
aestimo-3.0.0.dist-info/top_level.txt
aestimo-3.0.0.dist-info/RECORD
